NetworkManager.py
er_python_networkmanager-2.3.dist-info/COPYING
er_python_networkmanager-2.3.dist-info/METADATA
er_python_networkmanager-2.3.dist-info/WHEEL
er_python_networkmanager-2.3.dist-info/top_level.txt
er_python_networkmanager-2.3.dist-info/RECORD
